library_manager/__init__.py
library_manager/library_manager.py
library_manager/llibrary_manager.py
library_manager/main.py
library_manager_ausaf-0.3.0.dist-info/METADATA
library_manager_ausaf-0.3.0.dist-info/WHEEL
library_manager_ausaf-0.3.0.dist-info/entry_points.txt
library_manager_ausaf-0.3.0.dist-info/top_level.txt
library_manager_ausaf-0.3.0.dist-info/RECORD
